bhatools/__init__.py
bhatools/globals.py
bhatools-0.1.0.dist-info/METADATA
bhatools-0.1.0.dist-info/WHEEL
bhatools-0.1.0.dist-info/RECORD
