Metadata-Version: 2.1
Name: bhatools
Version: 0.1.0
Summary: Various tools used by Vaibhav
Author: Vaibhav Bhandari
Author-email: vaibhavb@gmail.com
Requires-Python: >=3.11,<4.0
Classifier: Programming Language :: Python :: 3
Classifier: Programming Language :: Python :: 3.11
Classifier: Programming Language :: Python :: 3.12
